Metadata-Version: 2.1
Name: learndatascience
Version: 1.0.0
Summary: created this to learn how packages are created.
Author: Anil
